{  
   "data":[  
{"Name":"01 - Crop and animal production, hunting and related service activities"},
{"Name":"02 - Forestry and logging"},
{"Name":"03 - Fishing and aquaculture"},
{"Name":"05 - Mining of coal and lignite"},
{"Name":"06 - Extraction of crude petroleum and natural gas"},
{"Name":"07 - Mining of metal ores"},
{"Name":"08 - Other mining and quarrying"},
{"Name":"09 - Mining support service activities"},
{"Name":"10 - Manufacture of food products"},
{"Name":"11 - Manufacture of beverages"},
{"Name":"12 - Manufacture of tobacco products"},
{"Name":"13 - Manufacture of textiles"},
{"Name":"14 - Manufacture of wearing apparel"},
{"Name":"15 - Manufacture of leather and related products"},
{"Name":"16 - Manufacture of wood and of products of wood and cork, except furniture; manufacture of articles of straw and plaiting materials"},
{"Name":"17 - Manufacture of paper and paper products"},
{"Name":"18 - Printing and reproduction of recorded media"},
{"Name":"19 - Manufacture of coke and refined petroleum products"},
{"Name":"20 - Manufacture of chemicals and chemical products"},
{"Name":"21 - Manufacture of basic pharmaceutical products and pharmaceutical preparations"},
{"Name":"22 - Manufacture of rubber and plastics products"},
{"Name":"23 - Manufacture of other non-metallic mineral products"},
{"Name":"24 - Manufacture of basic metals"},
{"Name":"25 - Manufacture of fabricated metal products, except machinery and equipment"},
{"Name":"26 - Manufacture of computer, electronic and optical products"},
{"Name":"27 - Manufacture of electrical equipment"},
{"Name":"28 - Manufacture of machinery and equipment n.e.c."},
{"Name":"29 - Manufacture of motor vehicles, trailers and semi-trailers"},
{"Name":"30 - Manufacture of other transport equipment"},
{"Name":"31 - Manufacture of furniture"},
{"Name":"32 - Other manufacturing"},
{"Name":"33 - Repair and installation of machinery and equipment"},
{"Name":"35 - Electricity, gas, steam and air conditioning supply"},
{"Name":"36 - Water collection, treatment and supply"},
{"Name":"37 - Sewerage"},
{"Name":"38 - Waste collection, treatment and disposal activities; materials recovery"},
{"Name":"39 - Remediation activities and other waste management services"},
{"Name":"41 - Construction of buildings"},
{"Name":"42 - Civil engineering"},
{"Name":"43 - Specialized construction activities"},
{"Name":"45 - Wholesale and retail trade and repair of motor vehicles and motorcycles"},
{"Name":"46 - Wholesale trade, except of motor vehicles and motorcycles"},
{"Name":"47 - Retail trade, except of motor vehicles and motorcycles"},
{"Name":"49 - Land transport and transport via pipelines"},
{"Name":"50 - Water transport"},
{"Name":"51 - Air transport"},
{"Name":"52 - Warehousing and support activities for transportation"},
{"Name":"53 - Postal and courier activities"},
{"Name":"55 - Accommodation"},
{"Name":"56 - Food and beverage service activities"},
{"Name":"58 - Publishing activities"},
{"Name":"59 - Motion picture, video and television programme production, sound recording and music publishing activities"},
{"Name":"60 - Programming and broadcasting activities"},
{"Name":"61 - Telecommunications"},
{"Name":"62 - Computer programming, consultancy and related activities"},
{"Name":"63 - Information service activities"},
{"Name":"64 - Financial service activities, except insurance and pension funding"},
{"Name":"65 - Insurance, reinsurance and pension funding, except compulsory social security"},
{"Name":"66 - Activities auxiliary to financial service and insurance activities"},
{"Name":"68 - Real estate activities"},
{"Name":"69 - Legal and accounting activities"},
{"Name":"70 - Activities of head offices; management consultancy activities"},
{"Name":"71 - Architectural and engineering activities; technical testing and analysis"},
{"Name":"72 - Scientific research and development"},
{"Name":"73 - Advertising and market research"},
{"Name":"74 - Other professional, scientific and technical activities"},
{"Name":"75 - Veterinary activities"},
{"Name":"77 - Rental and leasing activities"},
{"Name":"78 - Employment activities"},
{"Name":"79 - Travel agency, tour operator, reservation service and related activities"},
{"Name":"80 - Security and investigation activities"},
{"Name":"81 - Services to buildings and landscape activities"},
{"Name":"82 - Office administrative, office support and other business support activities"},
{"Name":"84 - Public administration and defence; compulsory social security"},
{"Name":"85 - Education"},
{"Name":"86 - Human health activities"},
{"Name":"87 - Residential care activities"},
{"Name":"88 - Social work activities without accommodation"},
{"Name":"90 - Creative, arts and entertainment activities"},
{"Name":"91 - Libraries, archives, museums and other cultural activities"},
{"Name":"92 - Gambling and betting activities"},
{"Name":"93 - Sports activities and amusement and recreation activities"},
{"Name":"94 - Activities of membership organizations"},
{"Name":"95 - Repair of computers and personal and household goods"},
{"Name":"96 - Other personal service activities"},
{"Name":"97 - Activities of households as employers of domestic personnel"},
{"Name":"98 - Undifferentiated goods- and services-producing activities of private households for own use"},
{"Name":"99 - Activities of extraterritorial organizations and bodies"}
   ]
}